pyVHDLParser/Base.py
pyVHDLParser/Decorators.py
pyVHDLParser/Functions.py
pyVHDLParser/__init__.py
pyVHDLParser/Blocks/Comment.py
pyVHDLParser/Blocks/Common.py
pyVHDLParser/Blocks/Exception.py
pyVHDLParser/Blocks/Expression.py
pyVHDLParser/Blocks/Generic.py
pyVHDLParser/Blocks/Generic1.py
pyVHDLParser/Blocks/InterfaceObject.py
pyVHDLParser/Blocks/__init__.py
pyVHDLParser/Blocks/Assignment/SignalAssignment.py
pyVHDLParser/Blocks/Assignment/VariableAssignment.py
pyVHDLParser/Blocks/Assignment/__init__.py
pyVHDLParser/Blocks/Attribute/AttributeDeclaration.py
pyVHDLParser/Blocks/Attribute/AttributeSpecification.py
pyVHDLParser/Blocks/Attribute/__init__.py
pyVHDLParser/Blocks/ControlStructure/Case.py
pyVHDLParser/Blocks/ControlStructure/Exit.py
pyVHDLParser/Blocks/ControlStructure/ForLoop.py
pyVHDLParser/Blocks/ControlStructure/If.py
pyVHDLParser/Blocks/ControlStructure/Next.py
pyVHDLParser/Blocks/ControlStructure/Null.py
pyVHDLParser/Blocks/ControlStructure/Return.py
pyVHDLParser/Blocks/ControlStructure/WhileLoop.py
pyVHDLParser/Blocks/ControlStructure/__init__.py
pyVHDLParser/Blocks/Generate/CaseGenerate.py
pyVHDLParser/Blocks/Generate/ForGenerate.py
pyVHDLParser/Blocks/Generate/IfGenerate.py
pyVHDLParser/Blocks/Generate/__init__.py
pyVHDLParser/Blocks/Instantiation/EntityInstantiation.py
pyVHDLParser/Blocks/Instantiation/FunctionInstantiation.py
pyVHDLParser/Blocks/Instantiation/PackageInstantiation.py
pyVHDLParser/Blocks/Instantiation/ProcedureInstantiation.py
pyVHDLParser/Blocks/Instantiation/__init__.py
pyVHDLParser/Blocks/List/GenericList.py
pyVHDLParser/Blocks/List/GenericMapList.py
pyVHDLParser/Blocks/List/ParameterList.py
pyVHDLParser/Blocks/List/PortList.py
pyVHDLParser/Blocks/List/PortMapList.py
pyVHDLParser/Blocks/List/SensitivityList.py
pyVHDLParser/Blocks/List/__init__.py
pyVHDLParser/Blocks/Object/Constant.py
pyVHDLParser/Blocks/Object/File.py
pyVHDLParser/Blocks/Object/SharedVariable.py
pyVHDLParser/Blocks/Object/Signal.py
pyVHDLParser-0.7.0.dist-info/LICENSE.md
pyVHDLParser-0.7.0.dist-info/METADATA
pyVHDLParser-0.7.0.dist-info/WHEEL
pyVHDLParser-0.7.0.dist-info/entry_points.txt
pyVHDLParser-0.7.0.dist-info/top_level.txt
pyVHDLParser-0.7.0.dist-info/RECORD
