Metadata-Version: 2.1
Name: pyVHDLParser
Version: 0.7.0
Summary: A streaming-based VHDL parser.
Home-page: https://GitHub.com/Paebbels/pyVHDLParser
Author: Patrick Lehmann
Author-email: Paebbels@gmail.com
License: Apache-2.0
Project-URL: Documentation, https://Paebbels.GitHub.io/pyVHDLParser
Project-URL: Source Code, https://GitHub.com/Paebbels/pyVHDLParser
Project-URL: Issue Tracker, https://GitHub.com/Paebbels/pyVHDLParser/issues
Keywords: Python3 VHDL Parser
Classifier: Operating System :: OS Independent
Classifier: Intended Audience :: Developers
Classifier: Topic :: Utilities
Classifier: Operating System :: OS Independent
Classifier: Intended Audience :: Developers
Classifier: Topic :: Scientific/Engineering :: Electronic Design Automation (EDA)
Classifier: Topic :: Software Development :: Code Generators
Classifier: Topic :: Software Development :: Compilers
Classifier: Topic :: Software Development :: Testing
Classifier: Topic :: Utilities
Classifier: License :: OSI Approved :: Apache Software License
Classifier: Programming Language :: Python :: 3 :: Only
Classifier: Programming Language :: Python :: 3.7
Classifier: Programming Language :: Python :: 3.8
Classifier: Programming Language :: Python :: 3.9
Classifier: Programming Language :: Python :: 3.10
Classifier: Programming Language :: Python :: 3.11
Classifier: Development Status :: 2 - Pre-Alpha
Requires-Python: >=3.7
License-File: LICENSE.md
Requires-Dist: pyTooling.TerminalUI (>=1.5.9)
Requires-Dist: colorama (>=0.4.6)
Requires-Dist: pyAttributes (>=2.5.1)
Requires-Dist: py-flags (>=1.1.4)
Requires-Dist: pyTooling (>=2.12.3)
Requires-Dist: pyVHDLModel (==0.23.0)
Provides-Extra: all
Requires-Dist: pyTooling.TerminalUI (>=1.5.9) ; extra == 'all'
Requires-Dist: sphinxcontrib-mermaid (>=0.8.0) ; extra == 'all'
Requires-Dist: sphinx-autodoc-typehints (>=1.12.0) ; extra == 'all'
Requires-Dist: sphinx-fontawesome (>=0.0.6) ; extra == 'all'
Requires-Dist: colorama (>=0.4.6) ; extra == 'all'
Requires-Dist: autoapi ; extra == 'all'
Requires-Dist: pyAttributes (>=2.5.1) ; extra == 'all'
Requires-Dist: py-flags (>=1.1.4) ; extra == 'all'
Requires-Dist: pyTooling (>=2.12.3) ; extra == 'all'
Requires-Dist: btd.sphinx.autoprogram (>=0.1.7.post1) ; extra == 'all'
Requires-Dist: sphinx (<6.0,>=5.3) ; extra == 'all'
Requires-Dist: pyVHDLModel (==0.23.0) ; extra == 'all'
Provides-Extra: doc
Requires-Dist: pyTooling.TerminalUI (>=1.5.9) ; extra == 'doc'
Requires-Dist: sphinxcontrib-mermaid (>=0.8.0) ; extra == 'doc'
Requires-Dist: sphinx-autodoc-typehints (>=1.12.0) ; extra == 'doc'
Requires-Dist: sphinx-fontawesome (>=0.0.6) ; extra == 'doc'
Requires-Dist: colorama (>=0.4.6) ; extra == 'doc'
Requires-Dist: autoapi ; extra == 'doc'
Requires-Dist: pyAttributes (>=2.5.1) ; extra == 'doc'
Requires-Dist: py-flags (>=1.1.4) ; extra == 'doc'
Requires-Dist: pyTooling (>=2.12.3) ; extra == 'doc'
Requires-Dist: btd.sphinx.autoprogram (>=0.1.7.post1) ; extra == 'doc'
Requires-Dist: sphinx (<6.0,>=5.3) ; extra == 'doc'
Requires-Dist: pyVHDLModel (==0.23.0) ; extra == 'doc'
